public_registry_pb2.py
public_registry_pb2_grpc.py
alpha_public_registry_grpc-1.0.3.dist-info/METADATA
alpha_public_registry_grpc-1.0.3.dist-info/WHEEL
alpha_public_registry_grpc-1.0.3.dist-info/top_level.txt
alpha_public_registry_grpc-1.0.3.dist-info/RECORD
