Metadata-Version: 2.1
Name: alpha-public-registry-grpc
Version: 1.0.3
Summary: gRPC code for alpha public registry client
Home-page: https://gitlab.com/alphaticks/alpha-public-registry-grpc
Author: Alphaticks
License: copyright
